hockeyjockey/__init__.py
hockeyjockey/config.py
hockeyjockey/jockey.py
hockeyjockey/api/__init__.py
hockeyjockey/api/statsapi.py
hockeyjockey/automation/__init__.py
hockeyjockey/automation/capture.py
hockeyjockey/exceptions/__init__.py
hockeyjockey/exceptions/exceptions.py
hockeyjockey/models/__init__.py
hockeyjockey/models/game.py
hockeyjockey/models/team.py
hockeyjockey/models/team_stats.py
hockeyjockey/utilities/__init__.py
hockeyjockey/utilities/date.py
hockeyjockey/utilities/db.py
hockeyjockey/utilities/file.py
hockeyjockey/utilities/stats.py
hockeyjockey-1.2.dist-info/LICENSE.TXT
hockeyjockey-1.2.dist-info/METADATA
hockeyjockey-1.2.dist-info/WHEEL
hockeyjockey-1.2.dist-info/top_level.txt
hockeyjockey-1.2.dist-info/RECORD
