Metadata-Version: 2.1
Name: hockeyjockey
Version: 1.2
Summary: A menu-driven console-based application for analyzing NHL hockey games.
Home-page: https://gitlab.com/ricoflow/hockeyjockey
Author: Randall Speake
Author-email: ranspeake@gmail.com
License: License :: OSI Approved :: GNU General Public License v3 (GPLv3)
Platform: UNKNOWN
Requires-Dist: decorest
Requires-Dist: ansicolors
Requires-Dist: mysql-connector-python
Requires-Dist: menyou
